MANIFEST.in
README.rst
setup.py
BrickBreaker/__init__.py
BrickBreaker/__init__.pyc
BrickBreaker/ball.py
BrickBreaker/ball.pyc
BrickBreaker/brick_breaker.py
BrickBreaker/double_pad.py
BrickBreaker/highscore.py
BrickBreaker/highscore.pyc
BrickBreaker/level.py
BrickBreaker/level.pyc
BrickBreaker/pad.py
BrickBreaker/pad.pyc
BrickBreaker/Bricks/__init__.py
BrickBreaker/Bricks/__init__.pyc
BrickBreaker/Bricks/ball_brick.py
BrickBreaker/Bricks/ball_brick.pyc
BrickBreaker/Bricks/brick.py
BrickBreaker/Bricks/brick.pyc
BrickBreaker/Bricks/life_brick.py
BrickBreaker/Bricks/life_brick.pyc
BrickBreaker/Bricks/size_brick.py
BrickBreaker/Bricks/size_brick.pyc
BrickBreaker/Bricks/speed_brick.py
BrickBreaker/Bricks/speed_brick.pyc
BrickBreaker/Bricks/__pycache__/__init__.cpython-36.pyc
BrickBreaker/Bricks/__pycache__/ball_brick.cpython-36.pyc
BrickBreaker/Bricks/__pycache__/brick.cpython-36.pyc
BrickBreaker/Bricks/__pycache__/life_brick.cpython-36.pyc
BrickBreaker/Bricks/__pycache__/size_brick.cpython-36.pyc
BrickBreaker/Bricks/__pycache__/speed_brick.cpython-36.pyc
BrickBreaker/Scenes/__init__.py
BrickBreaker/Scenes/controls_scene.py
BrickBreaker/Scenes/game_over_scene.py
BrickBreaker/Scenes/game_rules_scene.py
BrickBreaker/Scenes/highscore_scene.py
BrickBreaker/Scenes/main_menu_scene.py
BrickBreaker/Scenes/playing_game_scene.py
BrickBreaker/Scenes/scene.py
BrickBreaker/Scenes/win_scene.py
BrickBreaker/Scenes/__pycache__/__init__.cpython-36.pyc
BrickBreaker/Scenes/__pycache__/controls_scene.cpython-36.pyc
BrickBreaker/Scenes/__pycache__/game_over_scene.cpython-36.pyc
BrickBreaker/Scenes/__pycache__/game_rules_scene.cpython-36.pyc
BrickBreaker/Scenes/__pycache__/highscore_scene.cpython-36.pyc
BrickBreaker/Scenes/__pycache__/main_menu_scene.cpython-36.pyc
BrickBreaker/Scenes/__pycache__/playing_game_scene.cpython-36.pyc
BrickBreaker/Scenes/__pycache__/scene.cpython-36.pyc
BrickBreaker/Scenes/__pycache__/win_scene.cpython-36.pyc
BrickBreaker/Shared/__init__.py
BrickBreakerGame.egg-info/PKG-INFO
BrickBreakerGame.egg-info/SOURCES.txt
BrickBreakerGame.egg-info/dependency_links.txt
BrickBreakerGame.egg-info/entry_points.txt
BrickBreakerGame.egg-info/requires.txt
BrickBreakerGame.egg-info/top_level.txt