Metadata-Version: 1.0
Name: BrickBreakerGame
Version: 0.2.5
Summary: Brick Breaker game
Home-page: https://github.com/Urosh91/BrickBreaker
Author: Uros Jevremović
Author-email: jevremovic.uros91@gmail.com
License: UNKNOWN
Platform: UNKNOWN
